tests/__init__.py
text2graphapi/__init__.py
text2graphapi/main.py
text2graphapi/test.py
text2graphapi/testing.py
text2graphapi/docs/source/conf.py
text2graphapi/src/Cooccurrence.py
text2graphapi/src/Graph.py
text2graphapi/src/GraphTransformation.py
text2graphapi/src/Heterogeneous.py
text2graphapi/src/IntegratedSyntacticGraph.py
text2graphapi/src/Preprocessing.py
text2graphapi/src/Utils.py
text2graphapi/src/__init__.py
text2graphapi/src/configs.py
text2graphapi/src/resources/stopwords_english.txt
text2graphapi/src/resources/stopwords_french.txt
text2graphapi/src/resources/stopwords_spanish.txt
text2graphapi-0.2.0.dist-info/LICENSE.txt
text2graphapi-0.2.0.dist-info/METADATA
text2graphapi-0.2.0.dist-info/WHEEL
text2graphapi-0.2.0.dist-info/top_level.txt
text2graphapi-0.2.0.dist-info/RECORD
