Metadata-Version: 2.1
Name: text2graphapi
Version: 0.2.0
Summary: Use this library to transform raw text into differents graph representations.
Home-page: 
Author: PLN-disca-iimas
Author-email: andric.valdez@gmail.com
License: MIT
Classifier: Intended Audience :: Developers
Classifier: License :: OSI Approved :: MIT License
Classifier: Programming Language :: Python :: 3
Classifier: Operating System :: OS Independent
License-File: LICENSE.txt
Requires-Dist: contractions
Requires-Dist: emoji
Requires-Dist: emot
Requires-Dist: flashtext
Requires-Dist: joblib
Requires-Dist: matplotlib
Requires-Dist: networkx
Requires-Dist: nltk
Requires-Dist: numpy
Requires-Dist: pandas
Requires-Dist: setuptools
Requires-Dist: sphinx
Requires-Dist: spacy
Requires-Dist: scipy
